universalCRC/__init__.py
universalCRC/crc.py
universal_crc-0.9.dist-info/licenses/LICENSE.txt
universal_crc-0.9.dist-info/METADATA
universal_crc-0.9.dist-info/WHEEL
universal_crc-0.9.dist-info/top_level.txt
universal_crc-0.9.dist-info/RECORD
