Metadata-Version: 2.4
Name: universal-crc
Version: 0.9
Summary: A universal CRC (8, 16, 32 or 64) computation tool
Home-page: https://github.com/JoramFC/universalCRC
Author: Joram Fillol-Carlini
Author-email: joram.fillolcarlini@laposte.net
Classifier: Programming Language :: Python :: 3
Classifier: Development Status :: 4 - Beta
Classifier: License :: OSI Approved :: MIT License
Classifier: Natural Language :: English
Classifier: Operating System :: OS Independent
Requires-Python: >=3.6,<4
License-File: LICENSE.txt
Dynamic: author
Dynamic: author-email
Dynamic: classifier
Dynamic: description
Dynamic: description-content-type
Dynamic: home-page
Dynamic: license-file
Dynamic: requires-python
Dynamic: summary
